{
  "date": "2026-04-25",
  "new_triples": [
    { "subject": "ent-evt-001", "predicate": "hostsAt", "object": "ent-venue-001", "source_id": "src-001", "date": "2026-04-25", "confidence": 0.95, "type": "explicit" },
    { "subject": "ent-evt-001", "predicate": "hostsAt", "object": "ent-venue-002", "source_id": "src-001", "date": "2026-04-25", "confidence": 0.95, "type": "explicit" },
    { "subject": "ent-evt-001", "predicate": "organizedBy", "object": "ent-org-001", "source_id": "src-001", "date": "2026-04-25", "confidence": 0.9, "type": "explicit" },
    { "subject": "ent-evt-001", "predicate": "organizedBy", "object": "ent-org-009", "source_id": "src-009", "date": "2026-04-25", "confidence": 0.85, "type": "explicit" },
    { "subject": "ent-evt-002", "predicate": "hostsAt", "object": "ent-venue-001", "source_id": "src-002", "date": "2026-04-25", "confidence": 0.95, "type": "explicit" },
    { "subject": "ent-evt-002", "predicate": "organizedBy", "object": "ent-org-003", "source_id": "src-002", "date": "2026-04-25", "confidence": 0.95, "type": "explicit" },
    { "subject": "ent-evt-002", "predicate": "partOfSeries", "object": "ent-evt-001", "source_id": "src-002", "date": "2026-04-25", "confidence": 0.9, "type": "explicit" },
    { "subject": "ent-evt-002", "predicate": "targetsAgeGroup", "object": "age-elem-low", "source_id": "src-002", "date": "2026-04-25", "confidence": 0.95, "type": "explicit" },
    { "subject": "ent-evt-002", "predicate": "targetsAgeGroup", "object": "age-elem-high", "source_id": "src-002", "date": "2026-04-25", "confidence": 0.95, "type": "explicit" },
    { "subject": "ent-evt-003", "predicate": "hostsAt", "object": "ent-venue-003", "source_id": "src-003", "date": "2026-04-25", "confidence": 0.85, "type": "explicit" },
    { "subject": "ent-evt-003", "predicate": "organizedBy", "object": "ent-org-004", "source_id": "src-003", "date": "2026-04-25", "confidence": 0.9, "type": "explicit" },
    { "subject": "ent-evt-003", "predicate": "targetsAgeGroup", "object": "age-infant", "source_id": "src-003", "date": "2026-04-25", "confidence": 0.95, "type": "explicit" },
    { "subject": "ent-evt-003", "predicate": "targetsAgeGroup", "object": "age-toddler", "source_id": "src-003", "date": "2026-04-25", "confidence": 0.95, "type": "explicit" },
    { "subject": "ent-evt-004", "predicate": "hostsAt", "object": "ent-venue-004", "source_id": "src-004", "date": "2026-04-25", "confidence": 0.95, "type": "explicit" },
    { "subject": "ent-evt-004", "predicate": "organizedBy", "object": "ent-org-005", "source_id": "src-004", "date": "2026-04-25", "confidence": 0.95, "type": "explicit" },
    { "subject": "ent-evt-004", "predicate": "targetsAgeGroup", "object": "age-elem-low", "source_id": "src-004", "date": "2026-04-25", "confidence": 0.9, "type": "explicit" },
    { "subject": "ent-evt-004", "predicate": "targetsAgeGroup", "object": "age-elem-high", "source_id": "src-004", "date": "2026-04-25", "confidence": 0.9, "type": "explicit" },
    { "subject": "ent-evt-005", "predicate": "organizedBy", "object": "ent-org-006", "source_id": "src-005", "date": "2026-04-25", "confidence": 0.9, "type": "explicit" },
    { "subject": "ent-evt-006", "predicate": "hostsAt", "object": "ent-venue-006", "source_id": "src-006", "date": "2026-04-25", "confidence": 0.95, "type": "explicit" },
    { "subject": "ent-evt-006", "predicate": "organizedBy", "object": "ent-org-007", "source_id": "src-006", "date": "2026-04-25", "confidence": 0.95, "type": "explicit" },
    { "subject": "ent-evt-006", "predicate": "targetsAgeGroup", "object": "age-family", "source_id": "src-006", "date": "2026-04-25", "confidence": 0.9, "type": "explicit" },
    { "subject": "ent-evt-007", "predicate": "organizedBy", "object": "ent-org-004", "source_id": "src-007", "date": "2026-04-25", "confidence": 0.9, "type": "explicit" },
    { "subject": "ent-evt-008", "predicate": "hostsAt", "object": "ent-venue-007", "source_id": "src-008", "date": "2026-04-25", "confidence": 0.85, "type": "explicit" },
    { "subject": "ent-evt-008", "predicate": "hostsAt", "object": "ent-venue-010", "source_id": "src-008", "date": "2026-04-25", "confidence": 0.85, "type": "explicit" },
    { "subject": "ent-evt-008", "predicate": "organizedBy", "object": "ent-org-008", "source_id": "src-008", "date": "2026-04-25", "confidence": 0.85, "type": "explicit" },
    { "subject": "ent-evt-009", "predicate": "hostsAt", "object": "ent-venue-011", "source_id": "src-010", "date": "2026-04-25", "confidence": 0.95, "type": "explicit" },
    { "subject": "ent-evt-009", "predicate": "organizedBy", "object": "ent-org-010", "source_id": "src-010", "date": "2026-04-25", "confidence": 0.95, "type": "explicit" },
    { "subject": "ent-evt-009", "predicate": "targetsAgeGroup", "object": "age-toddler", "source_id": "src-010", "date": "2026-04-25", "confidence": 0.9, "type": "explicit" },
    { "subject": "ent-evt-009", "predicate": "targetsAgeGroup", "object": "age-elem-low", "source_id": "src-010", "date": "2026-04-25", "confidence": 0.9, "type": "explicit" },
    { "subject": "ent-evt-010", "predicate": "organizedBy", "object": "ent-org-011", "source_id": "src-011", "date": "2026-04-25", "confidence": 0.9, "type": "explicit" },
    { "subject": "ent-evt-010", "predicate": "targetsAgeGroup", "object": "age-toddler", "source_id": "src-011", "date": "2026-04-25", "confidence": 0.85, "type": "explicit" },
    { "subject": "ent-venue-001", "predicate": "locatedIn", "object": "dong-doryong", "source_id": "src-001", "date": "2026-04-25", "confidence": 0.95, "type": "explicit" },
    { "subject": "ent-venue-002", "predicate": "locatedIn", "object": "dong-doryong", "source_id": "src-001", "date": "2026-04-25", "confidence": 0.95, "type": "explicit" },
    { "subject": "ent-venue-004", "predicate": "locatedIn", "object": "dong-doryong", "source_id": "src-004", "date": "2026-04-25", "confidence": 0.95, "type": "explicit" },
    { "subject": "ent-venue-005", "predicate": "locatedIn", "object": "dong-doryong", "source_id": "src-005", "date": "2026-04-25", "confidence": 0.95, "type": "explicit" },
    { "subject": "ent-venue-006", "predicate": "locatedIn", "object": "dong-doryong", "source_id": "src-006", "date": "2026-04-25", "confidence": 0.95, "type": "explicit" },
    { "subject": "ent-venue-007", "predicate": "locatedIn", "object": "dong-gwanpyeong", "source_id": "src-008", "date": "2026-04-25", "confidence": 0.95, "type": "explicit" },
    { "subject": "ent-venue-008", "predicate": "locatedIn", "object": "dong-noeun", "source_id": "src-007", "date": "2026-04-25", "confidence": 0.9, "type": "explicit" },
    { "subject": "ent-venue-009", "predicate": "locatedIn", "object": "dong-munji", "source_id": "src-007", "date": "2026-04-25", "confidence": 0.9, "type": "explicit" },
    { "subject": "ent-venue-010", "predicate": "locatedIn", "object": "dong-jeonmin", "source_id": "src-008", "date": "2026-04-25", "confidence": 0.9, "type": "explicit" },
    { "subject": "ent-venue-011", "predicate": "locatedIn", "object": "dong-noeun", "source_id": "src-010", "date": "2026-04-25", "confidence": 0.95, "type": "explicit" },
    { "subject": "ent-org-004", "predicate": "operates", "object": "ent-venue-003", "source_id": "src-003", "date": "2026-04-25", "confidence": 0.9, "type": "explicit" },
    { "subject": "ent-org-005", "predicate": "operates", "object": "ent-venue-004", "source_id": "src-004", "date": "2026-04-25", "confidence": 0.95, "type": "explicit" },
    { "subject": "ent-org-006", "predicate": "operates", "object": "ent-venue-005", "source_id": "src-005", "date": "2026-04-25", "confidence": 0.95, "type": "explicit" },
    { "subject": "ent-org-007", "predicate": "operates", "object": "ent-venue-006", "source_id": "src-006", "date": "2026-04-25", "confidence": 0.95, "type": "explicit" },
    { "subject": "ent-org-010", "predicate": "operates", "object": "ent-venue-011", "source_id": "src-010", "date": "2026-04-25", "confidence": 0.95, "type": "explicit" }
  ],
  "updated_triples": [
    { "subject": "ent-evt-001", "predicate": "organizedBy", "object": "ent-org-009", "source_id": "src-009", "date": "2026-04-25", "confidence": 0.85, "type": "explicit", "note": "과학기술정보통신부 공동운영 확인 (37만 성료 보도)" }
  ],
  "inferred_triples": [
    { "subject": "ent-evt-001", "predicate": "visitCombo", "object": "ent-evt-006", "confidence": 0.85, "type": "inferred", "rule": "same_dong_combo", "note": "도룡동 동일 소재" },
    { "subject": "ent-evt-004", "predicate": "visitCombo", "object": "ent-evt-006", "confidence": 0.85, "type": "inferred", "rule": "same_dong_combo", "note": "도룡동 오후-야간 연계" },
    { "subject": "ent-venue-001", "predicate": "nearby", "object": "ent-venue-004", "confidence": 0.9, "type": "inferred", "rule": "proximity", "note": "도룡동 과학벨트 도보 연계" },
    { "subject": "ent-venue-001", "predicate": "nearby", "object": "ent-venue-006", "confidence": 0.9, "type": "inferred", "rule": "proximity", "note": "도룡동 과학벨트" },
    { "subject": "ent-venue-004", "predicate": "nearby", "object": "ent-venue-005", "confidence": 0.95, "type": "inferred", "rule": "proximity", "note": "동일 부지" },
    { "subject": "ent-evt-006", "predicate": "rainyFallbackFor", "object": "ent-evt-001", "confidence": 0.75, "type": "inferred", "rule": "indoor_rainy_fallback", "note": "천문대(실내) = 페스티벌(야외) 대체" },
    { "subject": "ent-evt-009", "predicate": "visitCombo", "object": "ent-evt-007", "confidence": 0.7, "type": "inferred", "rule": "same_dong_combo", "note": "노은동 어린이회관 + 노은도서관 묶음 가능" },
    { "subject": "ent-evt-004", "predicate": "kidFriendlyBoost", "object": "+0.2", "confidence": 0.9, "type": "inferred", "rule": "operator_kid_friendliness", "note": "과학관 운영" },
    { "subject": "ent-evt-003", "predicate": "kidFriendlyBoost", "object": "+0.2", "confidence": 0.9, "type": "inferred", "rule": "operator_kid_friendliness", "note": "도서관 운영" },
    { "subject": "ent-evt-009", "predicate": "kidFriendlyBoost", "object": "+0.2", "confidence": 0.9, "type": "inferred", "rule": "operator_kid_friendliness", "note": "어린이 전용 시설" }
  ],
  "stats": {
    "new_nodes": 5,
    "new_edges": 11,
    "inferred_edges": 10
  }
}
